Metadata-Version: 1.0
Name: tvlc
Version: 0.4
Summary: Stream movies directly from torrent
Home-page: https://github.com/RatulGhosh/movie-stream
Author: Ratul Ghosh
Author-email: ratulghoshr@gmail.com
License: MIT
Platform: UNKNOWN
